pymono/Base.py
pymono/Errors.py
pymono/Mono.py
pymono/User.py
pymono/__init__.py
tests/__init__.py
tests/test_mono.py
Py_Mono-0.0.1.dist-info/LICENSE.MD
Py_Mono-0.0.1.dist-info/METADATA
Py_Mono-0.0.1.dist-info/WHEEL
Py_Mono-0.0.1.dist-info/top_level.txt
Py_Mono-0.0.1.dist-info/RECORD
