Metadata-Version: 2.1
Name: Py-Mono
Version: 0.0.1
Summary: Mono Python API wrapper
Home-page: https://github.com/hamzzy/Mono-Python
Author: Ibrahim Hamzat
Author-email: hamat.ibrahim3@gmail.com
License: UNKNOWN
Platform: UNKNOWN
Classifier: Programming Language :: Python :: 3
Classifier: License :: OSI Approved :: MIT License
Classifier: Operating System :: OS Independent
Requires-Python: >=3.6
